teable_nocodb/__about__.py
teable_nocodb/__init__.py
teable_nocodb/data_type.py
teable_nocodb/nocodb.py
teable_nocodb/py.typed
teable_nocodb/teable.py
teable_nocodb/utils.py
teable_nocodb-1.0.0.dist-info/METADATA
teable_nocodb-1.0.0.dist-info/WHEEL
teable_nocodb-1.0.0.dist-info/licenses/LICENSE.txt
teable_nocodb-1.0.0.dist-info/RECORD
