Metadata-Version: 2.3
Name: teable-nocodb
Version: 1.0.0
License: MIT
Requires-Python: >=3.8
